snake_dqn_core/__init__.py
snake_dqn_core/cli.py
snake_dqn_core/play_model.py
snake_dqn_core/snake_env.py
snake_dqn_core/train_doubling_dqn.py
snake_dqn_core/train_dqn.py
snake_dqn_core/train_dueling_dqn.py
snake_dqn_core/train_hybrid_dqn.py
snake_dqn_core/train_rainbow_dqn.py
snake_dqn-2.1.1.dist-info/METADATA
snake_dqn-2.1.1.dist-info/WHEEL
snake_dqn-2.1.1.dist-info/entry_points.txt
snake_dqn-2.1.1.dist-info/top_level.txt
snake_dqn-2.1.1.dist-info/RECORD
