Metadata-Version: 2.1
Name: snake-dqn
Version: 2.1.1
Summary: A simple DQN implementation for Snake game
Home-page: https://github.com/LacyCat/Snake_DQN
Author: LacyCat
Classifier: Programming Language :: Python :: 3
Classifier: License :: OSI Approved :: MIT License
Requires-Dist: torch>=2.0
Requires-Dist: pygame>=2.1.1
Requires-Dist: numpy
Requires-Dist: gym
Requires-Dist: tensorboard>=2.19.0
